django_dust_sensor-0.2.34.dist-info/metadata.json
django_dust_sensor-0.2.34.dist-info/DESCRIPTION.rst
django_dust_sensor-0.2.34.dist-info/METADATA
django_dust_sensor-0.2.34.dist-info/RECORD
django_dust_sensor-0.2.34.dist-info/top_level.txt
django_dust_sensor-0.2.34.dist-info/WHEEL
dust_sensor/__init__.py
dust_sensor/urls.py
dust_sensor/DustSensor.py
dust_sensor/tasks.py
dust_sensor/management/__init__.py
dust_sensor/management/commands/__init__.py
dust_sensor/management/commands/dust_measure.py
