Metadata-Version: 2.0
Name: django-dust-sensor
Version: 0.2.34
Summary: django dust sensor celery based measure tool
Home-page: https://webeye.services/
Author: Václav Rak
Author-email: rak@webeye.services
License: MIT License
Platform: UNKNOWN
Classifier: Topic :: Scientific/Engineering :: Atmospheric Science
Classifier: Topic :: System :: Monitoring
Classifier: Topic :: System :: Logging
Classifier: Framework :: Django
Classifier: License :: OSI Approved :: MIT License
Classifier: Operating System :: OS Independent
Classifier: Programming Language :: Python :: 2.7
